visionFusion/__init__.py
visionFusion/_models.py
visionFusion/_utils.py
visionfusion-0.1.8.dist-info/LICENSE
visionfusion-0.1.8.dist-info/METADATA
visionfusion-0.1.8.dist-info/WHEEL
visionfusion-0.1.8.dist-info/RECORD
