Metadata-Version: 2.1
Name: visionFusion
Version: 0.1.8
Summary: visionFusion é um conjunto de ferramentas de ocr para facilitar o processo de extração de texto em diferentes cenarios   
Author: Gpocas
Author-email: gpocas01@gmail.com
Requires-Python: >=3.11,<4.0
Classifier: Development Status :: 5 - Production/Stable
Classifier: Natural Language :: Portuguese (Brazilian)
Classifier: Programming Language :: Python :: 3
Classifier: Programming Language :: Python :: 3.11
Classifier: Programming Language :: Python :: 3.12
Classifier: Topic :: Education
Requires-Dist: google-cloud-vision (>=3.7.2,<4.0.0)
Requires-Dist: pillow (>=10.3.0,<11.0.0)
Requires-Dist: pyperclip (>=1.8.2,<2.0.0)
Requires-Dist: pytesseract (>=0.3.10,<0.4.0)
Project-URL: Bug Tracker, https://github.com/Gpocas/visionFusion/issues
Project-URL: Código, https://github.com/Gpocas/visionFusion
